<?xml version="1.0" encoding="utf-8"?>
<GameData>
	<Language_ko_KR>
		<Row Tag="TXT_KEY_NOTIFICATION_EVENT_MANDATE_OF_HEAVEN_CHOICE_1_S">
			<Text>{3_PlayerName}가 천명 탐구를 시작합니다.</Text>
		</Row>
		<Row Tag="TXT_KEY_NOTIFICATION_EVENT_MANDATE_OF_HEAVEN_CHOICE_1">
			<Text>{3_PlayerName}가 천명을 위한 투쟁에서 고대의 적에 대해 선전 캠페인을 시작합니다.</Text>
		</Row>
		<Row Tag="TXT_KEY_NOTIFICATION_EVENT_MANDATE_OF_HEAVEN_CHOICE_2_S">
			<Text>{3_PlayerName}가 천명 탐구를 계속하고 있습니다.</Text>
		</Row>
		<Row Tag="TXT_KEY_NOTIFICATION_EVENT_MANDATE_OF_HEAVEN_CHOICE_2">
			<Text>{3_PlayerName}의 군대가 지도자의 신성함을 완전히 믿고 있습니다!</Text>
		</Row>
		<Row Tag="TXT_KEY_NOTIFICATION_EVENT_MANDATE_OF_HEAVEN_CHOICE_3_S">
			<Text>{3_PlayerName}가 천명 탐구를 계속하고 있습니다.</Text>
		</Row>
		<Row Tag="TXT_KEY_NOTIFICATION_EVENT_MANDATE_OF_HEAVEN_CHOICE_3">
			<Text>{3_PlayerName}가 천명 탐구를 그들의 교회 문화에 더 깊이 배속시키고 있습니다.</Text>
		</Row>
		<Row Tag="TXT_KEY_NOTIFICATION_EVENT_MANDATE_OF_HEAVEN_CHOICE_4_S">
			<Text>{3_PlayerName}가 천명 탐구를 계속하고 있습니다.</Text>
		</Row>
		<Row Tag="TXT_KEY_NOTIFICATION_EVENT_MANDATE_OF_HEAVEN_CHOICE_4">
			<Text>{3_PlayerName}의 적의 뼈가 이제 천상의 왕좌 위에 영원히 걸려 있습니다.</Text>
		</Row>
		<Row Tag="TXT_KEY_NOTIFICATION_EVENT_MANDATE_OF_HEAVEN_CHOICE_5_S">
			<Text>{3_PlayerName}가 천명 탐구를 계속하고 있습니다.</Text>
		</Row>
		<Row Tag="TXT_KEY_NOTIFICATION_EVENT_MANDATE_OF_HEAVEN_CHOICE_5">
			<Text>{3_PlayerName}가 적을 숨겨진 곳에서 끌어내기 위해 요원들을 보내고 있습니다!</Text>
		</Row>
		<Row Tag="TXT_KEY_NOTIFICATION_EVENT_MANDATE_OF_HEAVEN_CHOICE_6_S">
			<Text>{3_PlayerName}가 천명 탐구를 완료했습니다!</Text>
		</Row>
		<Row Tag="TXT_KEY_NOTIFICATION_EVENT_MANDATE_OF_HEAVEN_CHOICE_6">
			<Text>{3_PlayerName}가 오랜 라이벌을 처형하여 천명의 권한을 확보했습니다!</Text>
		</Row>
		<Row Tag="TXT_KEY_EVENT_MANDATE_OF_HEAVEN_DESCRIPTION">
			<Text>불로장생의 영약</Text>
		</Row>
		<Row Tag="TXT_KEY_EVENT_MANDATE_OF_HEAVEN_HELP">
			<Text>제국 초기, 한 하찮은 약초학자가 불로장생의 영약을 발견했다고 궁전에 왔습니다. 이 영약으로 불로불사의 존재로 만들 수 있다고 주장했습니다. 우리가 그것을 필요로 하지 않았고, 다른 사람들이 우리의 지위에 오르기를 원하지 않았기 때문에 우리는 그를 처형했습니다.[NEWLINE][NEWLINE]이제 그가 부활했다는 소문이 있습니다. 이것은 용납할 수 없습니다! 이 유령을 찾아서 지하 세계로 되돌려 보내야 합니다!</Text>
		</Row>
		<Row Tag="TXT_KEY_EVENT_MANDATE_OF_HEAVEN_HELP_CHOICE_1">
			<Text>{1_YieldCost}의 새로운 교리를 발동하여, 당신의 사원과 천상의 왕좌가 +1 [ICON_PEACE] 신앙을 생성하게 합니다.</Text>
		</Row>
		<Row Tag="TXT_KEY_EVENT_MANDATE_OF_HEAVEN_HELP_CHOICE_2">
			<Text>{1_YieldCost}를 사용하여 유령의 추종자를 억제합니다. 모든 근접 및 총기 유닛이 제국의 손길 승진을 받습니다.</Text>
		</Row>
		<Row Tag="TXT_KEY_EVENT_MANDATE_OF_HEAVEN_HELP_CHOICE_3">
			<Text>{1_YieldCost}의 새로운 교리를 발동하여, 당신의 신앙으로 구매한 건물과 천상의 왕좌가 +1 [ICON_PEACE] 식량과 [ICON_PRODUCTION] 생산력을 생성하게 합니다.</Text>
		</Row>
		<Row Tag="TXT_KEY_EVENT_MANDATE_OF_HEAVEN_HELP_CHOICE_4">
			<Text>{1_YieldCost}의 길조의 의식을 시행합니다. 천상의 왕좌의 [ICON_PEACE] 신앙과 [ICON_CULTURE]가 10% 증가합니다.</Text>
		</Row>
		<Row Tag="TXT_KEY_EVENT_MANDATE_OF_HEAVEN_HELP_CHOICE_5">
			<Text>적을 능가하기 위해, 모든 [ICON_SPY] 스파이를 레벨업합니다.</Text>
		</Row>
		<Row Tag="TXT_KEY_EVENT_MANDATE_OF_HEAVEN_HELP_CHOICE_6">
			<Text>{1_YieldCost}를 모아 탐구를 완료합니다. 모든 농장과 마을이 +1 [ICON_PEACE] 신앙을 생성합니다.</Text>
		</Row>
		<Row Tag="TXT_KEY_EVENT_MANDATE_OF_HEAVEN_DESCRIPTION_CHOICE_1">
			<Text>이 적은 그 어떤 적과도 다릅니다. 그들은 인내심이 있으며 그림자 속에서 우리를 공격할 것입니다. 그들을 다치게 할 방법이 없습니다. 우리는 즉시 사람들을 그들에 대해 선동해야 합니다, 그렇지 않으면 모든 것이 잃어버릴 것입니다!</Text>
		</Row>
		<Row Tag="TXT_KEY_EVENT_MANDATE_OF_HEAVEN_DESCRIPTION_CHOICE_2">
			<Text>*천상의 왕좌의 격상이 광신적인 민병대 운동을 낳았습니다*[NEWLINE]이 열성적인 집단을 군대에 통합하면 제국에 큰 명예를 가져다줄 것입니다!</Text>
		</Row>
		<Row Tag="TXT_KEY_EVENT_MANDATE_OF_HEAVEN_DESCRIPTION_CHOICE_3">
			<Text>이 악마를 찾아야 합니다. 그가 어떻게 여전히 우리의 손아귀에서 벗어날 수 있습니까? 모든 전선에서 우리의 노력을 배가합시다!</Text>
		</Row>
		<Row Tag="TXT_KEY_EVENT_MANDATE_OF_HEAVEN_DESCRIPTION_CHOICE_4">
			<Text>드디어 진전을 이뤘습니다! 약초학자의 가장 헌신적인 하인이 우리의 손에 들어왔습니다. 그녀가 아는 모든 것을 알아내고, 그녀를 제 왕좌 위에 걸어놓으세요. 그녀의 끔찍한 운명이 제 적들에게 영원한 두려움을 주게 하겠습니다!</Text>
		</Row>
		<Row Tag="TXT_KEY_EVENT_MANDATE_OF_HEAVEN_DESCRIPTION_CHOICE_5">
			<Text>우리의 적이 코너에 몰렸습니다. 치명적인 타격이 곧 이뤄질 것입니다. 최고의 요원들을 보내, 그를 나에게 데려오세요!</Text>
		</Row>
		<Row Tag="TXT_KEY_EVENT_MANDATE_OF_HEAVEN_DESCRIPTION_CHOICE_6">
			<Text>이 사람을 직접 처형할 수 있었던 기쁨은 너무나도 바랄 수 없었습니다. 너무 오랜 시간이 지나서 그를 진정으로 인식하지 못했지만, 문제는 없습니다: 분명히 그가 맞았습니다. 이제 아무도 제 신성을 다투지 않습니다!</Text>
		</Row>
		<Row Tag="TXT_KEY_PROMOTION_MANDATE">
			<Text>제국의 손</Text>
		</Row>
		<Row Tag="TXT_KEY_PROMOTION_MANDATE_HELP">
			<Text>처치시 [ICON_GOLDEN_AGE] 황금기 점수 보상</Text>
		</Row>
	</Language_ko_KR>
</GameData>
